commonMethods_zhaozl_green/__init__.py
commonMethods_zhaozl_green/__version__.py
commonMethods_zhaozl_green/core.py
commonMethods_zhaozl_green/decoraters.py
commonMethods_zhaozl_green/toolbox/Method_bounceAnalyzer.py
commonMethods_zhaozl_green/toolbox/Method_comtradeParse.py
commonMethods_zhaozl_green/toolbox/Method_evennessDetermine.py
commonMethods_zhaozl_green/toolbox/Method_mysqlOperator.py
commonMethods_zhaozl_green/toolbox/Method_processBar.py
commonMethods_zhaozl_green/toolbox/Method_shuffle.py
commonMethods_zhaozl_green/toolbox/Method_timeTrans.py
commonMethods_zhaozl_green/toolbox/Method_trendAnalyzer.py
commonMethods_zhaozl_green/toolbox/__init__.py
commonMethods_zhaozl_green-2.6.dist-info/METADATA
commonMethods_zhaozl_green-2.6.dist-info/WHEEL
commonMethods_zhaozl_green-2.6.dist-info/top_level.txt
commonMethods_zhaozl_green-2.6.dist-info/RECORD
